{
	"pages": [{
			"path": "pages/moto-cms/home",
			"style": {
				"navigationBarTitleText": "机车圈-首页"
			}
		}, {
			"path": "pages/moto-cms/article-list",
			"style": {
				"navigationBarTitleText": "机车圈-发布记录"
			}
		}, {
			"path": "pages/moto-cms/article-draft",
			"style": {
				"navigationBarTitleText": "机车圈-草稿箱"
			}
		},
		{
			"path": "pages/login/login",
			"style": {
				"topWindow": false,
				"leftWindow": false,
				"navigationBarTitleText": ""
			}
		},
		{
			"path": "pages/moto-cms/rich-article-editor",
			"style": {
				"leftWindow": false,
				"navigationBarTitleText": "机车圈-长图文资讯编辑"
			}
		},
		{
			"path": "pages/moto-cms/normal-article-editor",
			"style": {
				"leftWindow": false,
				"navigationBarTitleText": "机车圈-动态编辑"
			}
		},
		{
			"path" : "pages/moto-interact/comment",
			"style" : 
			{
				"navigationBarTitleText" : "机车圈-评论管理"
			}
		},
		{
			"path" : "pages/moto-interact/like",
			"style" : 
			{
				"navigationBarTitleText" : "机车圈-点赞管理"
			}
		},
		{
			"path" : "pages/moto-interact/follow",
			"style" : 
			{
				"navigationBarTitleText" : "机车圈-关注管理"
			}
		},
		{
			"path" : "pages/user/user-center",
			"style" : 
			{
				"navigationBarTitleText" : "机车圈-用户中心"
			}
		},
		{
			"path" : "pages/user/user-feedback",
			"style" : 
			{
				"navigationBarTitleText" : "机车圈-用户反馈"
			}
		}
	],
	"topWindow": {
		"path": "windows/topWindow",
		"style": {
			"height": "60px"
		},
		"matchMedia": {
			"minWidth": 0
		}
	},
	"leftWindow": {
		"path": "windows/leftWindow",
		"style": {
			"width": "220px"
		},
		"matchMedia": {
			"minWidth": 0
		}
	},
	"globalStyle": {
		"navigationBarTextStyle": "black",
		"navigationBarTitleText": "uni-app",
		"navigationStyle": "custom",
		"navigationBarBackgroundColor": "#F8F8F8",
		"backgroundColor": "#F8F8F8"
	}
}