{
  "hash": "09c2d912",
  "configHash": "9265c7be",
  "lockfileHash": "34695d26",
  "browserHash": "30f3fd9d",
  "optimized": {
    "crypto-js/sha256": {
      "src": "../../../../../node_modules/crypto-js/sha256.js",
      "file": "crypto-js_sha256.js",
      "fileHash": "8c84585c",
      "needsInterop": true
    },
    "element-plus": {
      "src": "../../../../../node_modules/element-plus/es/index.mjs",
      "file": "element-plus.js",
      "fileHash": "920af530",
      "needsInterop": false
    },
    "jsencrypt": {
      "src": "../../../../../node_modules/jsencrypt/lib/index.js",
      "file": "jsencrypt.js",
      "fileHash": "1fb5286f",
      "needsInterop": false
    }
  },
  "chunks": {
    "chunk-POHSPSYC": {
      "file": "chunk-POHSPSYC.js"
    }
  }
}